image_similarity_core/__init__.py
image_similarity_core/image_similarity_core.py
image_similarity_core-0.1.0.dist-info/METADATA
image_similarity_core-0.1.0.dist-info/WHEEL
image_similarity_core-0.1.0.dist-info/top_level.txt
image_similarity_core-0.1.0.dist-info/RECORD
